mcp_openapi_proxy/__init__.py
mcp_openapi_proxy/handlers.py
mcp_openapi_proxy/logging_setup.py
mcp_openapi_proxy/openapi.py
mcp_openapi_proxy/server_fastmcp.py
mcp_openapi_proxy/server_lowlevel.py
mcp_openapi_proxy/types.py
mcp_openapi_proxy/utils.py
mseep_mcp_openapi_proxy-0.1.1.dist-info/licenses/LICENSE
mseep_mcp_openapi_proxy-0.1.1.dist-info/METADATA
mseep_mcp_openapi_proxy-0.1.1.dist-info/WHEEL
mseep_mcp_openapi_proxy-0.1.1.dist-info/entry_points.txt
mseep_mcp_openapi_proxy-0.1.1.dist-info/top_level.txt
mseep_mcp_openapi_proxy-0.1.1.dist-info/RECORD
