Metadata-Version: 2.4
Name: mseep-mcp-openapi-proxy
Version: 0.1.1
Summary: MCP server for exposing OpenAPI specifications as MCP tools.
Author-email: mseep <support@skydeck.ai>
Requires-Python: >=3.10
License-File: LICENSE
Requires-Dist: mcp[cli]>=1.2.0
Requires-Dist: python-dotenv>=1.0.1
Requires-Dist: requests>=2.25.0
Requires-Dist: fastapi>=0.100.0
Requires-Dist: pydantic>=2.0
Requires-Dist: prance>=23.6.21.0
Requires-Dist: openapi-spec-validator>=0.7.1
Requires-Dist: jmespath>=1.0.1
Provides-Extra: dev
Requires-Dist: pytest>=8.3.4; extra == "dev"
Requires-Dist: pytest-asyncio>=0.21.0; extra == "dev"
Requires-Dist: pytest-cov>=4.1.0; extra == "dev"
Dynamic: license-file
